rmas.libs/libvtkIOCore-2793225d.so.1
rmas.libs/libvtkFiltersImaging-4075d81f.so.1
rmas.libs/libpcl_features-0dd00ee4.so.1.7.2
rmas.libs/libXfixes-d274cb03.so.3.1.0
rmas.libs/libvtkImagingColor-991294a8.so.1
rmas.libs/libvtkRenderingLOD-9f5c9318.so.1
rmas.libs/libssl3-7d7debcb.so
rmas.libs/libvtkImagingStencil-85b8162e.so.1
rmas.libs/libvtkIOEnSight-4cf96fe6.so.1
rmas.libs/libgstapp-0-a5c3a46f.10.so.0.25.0
rmas.libs/libflann_cpp-6dc1243e.so.1.8.4
rmas.libs/libvtkViewsQt-b10d71aa.so.1
rmas.libs/libpcl_kdtree-3401fe10.so.1.7.2
rmas.libs/libnssutil3-5292dbaa.so
rmas.libs/libsasl2-84219a89.so.3.0.0
rmas.libs/libgstvideo-0-eb93982c.10.so.0.25.0
rmas.libs/libvtkFiltersStatistics-f3347078.so.1
rmas.libs/libvtkFiltersSMP-89307008.so.1
rmas.libs/libvtkInteractionImage-b640b0ee.so.1
rmas.libs/libvtkImagingSources-d2891199.so.1
rmas.libs/libvtkRenderingLIC-1fbdb398.so.1
rmas.libs/libgfortran-91cc3cb1.so.3.0.0
rmas.libs/libvtkIOImport-30c1d4cf.so.1
rmas.libs/libXt-4e660efc.so.6.0.0
rmas.libs/libvtkIOXML-09ecb7cf.so.1
rmas.libs/libpcl_common-9481f7a3.so.1.7.2
rmas.libs/libvtkverdict-a5d80810.so.1
rmas.libs/libvtkIOInfovis-58f6e51b.so.1
rmas.libs/libvtkCommonDataModel-a1bdc6df.so.1
rmas.libs/libvtkImagingFourier-0d0f2bb5.so.1
rmas.libs/libnspr4-4f93563e.so
rmas.libs/libvtkFiltersGeometry-46492571.so.1
rmas.libs/libvtkFiltersParallelImaging-a383391f.so.1
rmas.libs/libvtkIOParallel-4dc6826d.so.1
rmas.libs/libcom_err-2abe824b.so.2.1
rmas.libs/libffi-af4ed708.so.6.0.1
rmas.libs/libQtXmlPatterns-cd8f10c1.so.4.8.7
rmas.libs/libQtGui-46e392d9.so.4.8.7
rmas.libs/libvtkViewsGeovis-856fa959.so.1
rmas.libs/libpcl_sample_consensus-1c6ab2df.so.1.7.2
rmas.libs/libpcl_segmentation-01b2d9a2.so.1.7.2
rmas.libs/libvtkFiltersCore-8b388608.so.1
rmas.libs/libtre-bd715699.so.5.0.0
rmas.libs/libvtkWrappingPython27Core-905fdcd6.so.1
rmas.libs/libvtkDomainsChemistry-c8c1153c.so.1
rmas.libs/libQtSql-be5fefef.so.4.8.7
rmas.libs/libR-b0ffdf4f.so
rmas-0.1.2.dist-info/METADATA
rmas-0.1.2.dist-info/entry_points.txt
rmas-0.1.2.dist-info/WHEEL
rmas-0.1.2.dist-info/RECORD
rmas-0.1.2.dist-info/licenses/LICENSE
